pycof/.vscode/settings.json
pycof/__init__.py
pycof/about.py
pycof/data.py
pycof/format.py
pycof/init_template.py
pycof/misc.py
pycof/sql.py
pycof/sqlhelper.py
pycof-1.7.1.dist-info/METADATA
pycof-1.7.1.dist-info/WHEEL
pycof-1.7.1.dist-info/licenses/LICENSE
pycof-1.7.1.dist-info/RECORD
