Metadata-Version: 2.4
Name: PYCOF
Version: 1.7.1
Summary: PYthon COmmon Functions
License-Expression: MIT
License-File: LICENSE
Author: Florian Felice
Author-email: admin@florianfelice.com
Requires-Python: >=3.11,<3.13
Classifier: Programming Language :: Python :: 3
Classifier: Programming Language :: Python :: 3.11
Classifier: Programming Language :: Python :: 3.12
Provides-Extra: dev
Requires-Dist: black[jupyter] (>=25.1.0) ; extra == "dev"
Requires-Dist: boto3 (>=1.16.19)
Requires-Dist: bs4 (>=0.0.1)
Requires-Dist: colorlog (>=6.9.0)
Requires-Dist: dateparser (>=1.0.0)
Requires-Dist: flake8 (>=7.3.0) ; extra == "dev"
Requires-Dist: google-api-python-client (>=1.12.8)
Requires-Dist: google-auth (>=1.24.0)
Requires-Dist: google-auth-httplib2 (>=0.0.4)
Requires-Dist: google-auth-oauthlib (>=0.4.2)
Requires-Dist: httplib2 (>=0.18.1)
Requires-Dist: isort (>=5.13.2) ; extra == "dev"
Requires-Dist: matplotlib (>=3.1.1)
Requires-Dist: mypy (>=1.8.0) ; extra == "dev"
Requires-Dist: numpy (>=1.16.3)
Requires-Dist: pandas (>=2.3.2)
Requires-Dist: paramiko (>=4.0.0)
Requires-Dist: poetry-dynamic-versioning (>=1.0.0) ; extra == "dev"
Requires-Dist: pre-commit (>=3.0.0) ; extra == "dev"
Requires-Dist: psycopg2-binary (>=2.7.4)
Requires-Dist: pyarrow (>=21.0.0)
Requires-Dist: pymysql (>=0.9.3)
Requires-Dist: pytest (>=8.0.0) ; extra == "dev"
Requires-Dist: python-semantic-release (>=8.0.0) ; extra == "dev"
Requires-Dist: sqlalchemy (>=2.0.43)
Requires-Dist: sshtunnel (>=0.3.1)
Requires-Dist: tqdm (>=4.35.0)
Requires-Dist: xlrd (>=1.2.0)
Project-URL: Homepage, https://github.com/florianfelice/PYCOF
Project-URL: Repository, https://github.com/florianfelice/PYCOF
